Query2Vec/Query2Vec.py
Query2Vec/__init__.py
Query2Vec-0.1.0.dist-info/LICENSE
Query2Vec-0.1.0.dist-info/METADATA
Query2Vec-0.1.0.dist-info/WHEEL
Query2Vec-0.1.0.dist-info/top_level.txt
Query2Vec-0.1.0.dist-info/RECORD
