Metadata-Version: 2.1
Name: Query2Vec
Version: 0.1.0
Summary: Query2Vec package using word2vec and tfidf
Home-page: UNKNOWN
Author: Maede Ashofteh Barabadi
Author-email: 
License: UNKNOWN
Platform: UNKNOWN
Classifier: Programming Language :: Python :: 3
Classifier: License :: OSI Approved :: MIT License
Classifier: Operating System :: OS Independent
Requires-Python: >=3.6
